Metadata-Version: 1.0
Name: asttodotbuilder
Version: 1.1
Summary: Advanced python homework
Home-page: https://github.com/Karina5005/Python_HW2022/tree/master/hw01
Author: KarinaAnisimova
Author-email: anisimova5005@gmail.com
License: UNKNOWN
Platform: UNKNOWN
